cmsplugin_diff/__init__.py
cmsplugin_diff/admin.py
cmsplugin_diff/apps.py
cmsplugin_diff/cms_toolbar.py
cmsplugin_diff/middleware.py
cmsplugin_diff/models.py
cmsplugin_diff/urls.py
cmsplugin_diff/utils.py
cmsplugin_diff/views.py
cmsplugin_diff/migrations/0001_initial.py
cmsplugin_diff/migrations/__init__.py
cmsplugin_diff/templates/admin/cms/page/plugin/submit_line.html
cmsplugin_diff/templates/cmsplugin_diff/base.html
cmsplugin_diff/templates/cmsplugin_diff/diff.html
cmsplugin_diff/templates/cmsplugin_diff/editing_history.html
cmsplugin_diff/templates/cmsplugin_diff/editing_item.html
cmsplugin_diff/templates/cmsplugin_diff/page_history_list.html
cmsplugin_diff/templates/cmsplugin_diff/page_unpublished_list.html
cmsplugin_diff/templates/cmsplugin_diff/published_history.html
cmsplugin_diff/templates/cmsplugin_diff/site_history_list.html
cmsplugin_diff/templates/cmsplugin_diff/site_unpublished_list.html
cmsplugin_diff/templates/cmsplugin_diff/unpublished_list.html
cmsplugin_diff-2.0.0.dist-info/LICENSE
cmsplugin_diff-2.0.0.dist-info/METADATA
cmsplugin_diff-2.0.0.dist-info/WHEEL
cmsplugin_diff-2.0.0.dist-info/top_level.txt
cmsplugin_diff-2.0.0.dist-info/RECORD
