Metadata-Version: 2.2
Name: cmsplugin-diff
Version: 2.0.0
Summary: Extend django-cms with history and diff views.
Home-page: https://gitlab.com/doctormo/django-cmsplugin-diff
Author: Martin Owens
Author-email: doctormo@gmail.com
License: AGPLv3
Platform: linux
Classifier: Intended Audience :: Developers
Classifier: Intended Audience :: Information Technology
Classifier: Intended Audience :: System Administrators
Classifier: Programming Language :: Python
Classifier: Programming Language :: Python :: 3.7
License-File: LICENSE
Requires-Dist: django-cms>=3.11
Requires-Dist: diff_match_patch>=20121119
Dynamic: author
Dynamic: author-email
Dynamic: classifier
Dynamic: home-page
Dynamic: license
Dynamic: platform
Dynamic: requires-dist
Dynamic: summary
